private_join_and_compute-0.0.1.dist-info/METADATA
private_join_and_compute-0.0.1.dist-info/RECORD
private_join_and_compute-0.0.1.dist-info/WHEEL
private_join_and_compute/py/ciphers/ec_cipher.py
private_join_and_compute/py/crypto_util/converters.py
private_join_and_compute/py/crypto_util/elliptic_curve.py
private_join_and_compute/py/crypto_util/ssl_util.py
private_join_and_compute/py/crypto_util/supported_curves.py
private_join_and_compute/py/crypto_util/supported_hashes.py
