Metadata-Version: 2.1
Name: private_join_and_compute
Version: 0.0.1
Classifier: License :: OSI Approved :: Apache Software License
Requires-Dist: absl-py
Requires-Dist: six
